MANIFEST.in
README.md
VERSION.txt
geniegui.py
setup.py
geniegui.egg-info/PKG-INFO
geniegui.egg-info/SOURCES.txt
geniegui.egg-info/dependency_links.txt
geniegui.egg-info/top_level.txt